{
    "20250825": {
        "startdate": "20250824",
        "fullstartdate": "202508241600",
        "enddate": "20250825",
        "url": "/th?id=OHR.YellowstoneRiver_ZH-CN3716808579_1920x1080.jpg\u0026rf=LaDigue_1920x1080.jpg\u0026pid=hp",
        "urlbase": "/th?id=OHR.YellowstoneRiver_ZH-CN3716808579",
        "copyright": "方解石温泉区和黄石河，黄石国家公园，怀俄明州，美国 (© Rebecca L. Latson/Getty Images)",
        "copyrightlink": "https://www.bing.com/search?q=%E9%BB%84%E7%9F%B3%E6%B2%B3\u0026form=hpcapt\u0026mkt=zh-cn",
        "title": "从火山之源到河流之路",
        "quiz": "/search?q=Bing+homepage+quiz\u0026filters=WQOskey:%22HPQuiz_20250824_YellowstoneRiver%22\u0026FORM=HPQUIZ",
        "wp": true,
        "hsh": "22c32bfc3db56bce40a7f96c6f0fdf13",
        "drk": 1,
        "top": 1,
        "bot": 1,
        "hs": []
    }
}