{
    "20260602": {
        "startdate": "20260601",
        "fullstartdate": "202606011600",
        "enddate": "20260602",
        "url": "/th?id=OHR.Qinghai_ZH-CN9899656327_1920x1080.jpg\u0026rf=LaDigue_1920x1080.jpg\u0026pid=hp",
        "urlbase": "/th?id=OHR.Qinghai_ZH-CN9899656327",
        "copyright": "穿越西台吉乃尔湖的公路，青海省，中国 (© Kaicheng Xu/Getty Images)",
        "copyrightlink": "https://www.bing.com/search?q=%E4%B8%AD%E5%9B%BD%E6%9F%B4%E8%BE%BE%E6%9C%A8%E7%9B%86%E5%9C%B0\u0026form=hpcapt\u0026mkt=zh-cn",
        "title": "穿行于蓝色之间",
        "quiz": "/search?q=Bing+homepage+quiz\u0026filters=WQOskey:%22HPQuiz_20260601_Qinghai%22\u0026FORM=HPQUIZ",
        "wp": true,
        "hsh": "517ab01bc515a94d6619be1259b11e38",
        "drk": 1,
        "top": 1,
        "bot": 1,
        "hs": []
    }
}