{
    "20241117": {
        "startdate": "20241116",
        "fullstartdate": "202411161600",
        "enddate": "20241117",
        "url": "/th?id=OHR.RedStag_ZH-CN6403546321_1920x1080.jpg\u0026rf=LaDigue_1920x1080.jpg\u0026pid=hp",
        "urlbase": "/th?id=OHR.RedStag_ZH-CN6403546321",
        "copyright": "加里东林中的马鹿，阿夫力谷，苏格兰高地 (© Terry Whittaker/Alamy)",
        "copyrightlink": "https://www.bing.com/search?q=%E9%A9%AC%E9%B9%BF\u0026form=hpcapt\u0026mkt=zh-cn",
        "title": "苏格兰高地的马鹿",
        "quiz": "/search?q=Bing+homepage+quiz\u0026filters=WQOskey:%22HPQuiz_20241116_RedStag%22\u0026FORM=HPQUIZ",
        "wp": true,
        "hsh": "2dfe32ee45b2fe2ce39d0b084a0a7c9a",
        "drk": 1,
        "top": 1,
        "bot": 1,
        "hs": []
    }
}