{
    "20250112": {
        "startdate": "20250111",
        "fullstartdate": "202501111600",
        "enddate": "20250112",
        "url": "/th?id=OHR.CrescentTail_ZH-CN8283248964_1920x1080.jpg\u0026rf=LaDigue_1920x1080.jpg\u0026pid=hp",
        "urlbase": "/th?id=OHR.CrescentTail_ZH-CN8283248964",
        "copyright": "大堡礁的宝石大眼鲷鱼，澳大利亚 (© Fred Bavendam/Minden Pictures)",
        "copyrightlink": "https://www.bing.com/search?q=%E5%AE%9D%E7%9F%B3%E5%A4%A7%E7%9C%BC%E9%B2%B7%E9%B1%BC\u0026form=hpcapt\u0026mkt=zh-cn",
        "title": "深海中的锐利目光",
        "quiz": "/search?q=Bing+homepage+quiz\u0026filters=WQOskey:%22HPQuiz_20250111_CrescentTail%22\u0026FORM=HPQUIZ",
        "wp": true,
        "hsh": "9c7705f1e0589f7f4a5eb7a45b6badd8",
        "drk": 1,
        "top": 1,
        "bot": 1,
        "hs": []
    }
}