{
    "20250514": {
        "startdate": "20250513",
        "fullstartdate": "202505131600",
        "enddate": "20250514",
        "url": "/th?id=OHR.SardiniaFlavia_ZH-CN6784449568_1920x1080.jpg\u0026rf=LaDigue_1920x1080.jpg\u0026pid=hp",
        "urlbase": "/th?id=OHR.SardiniaFlavia_ZH-CN6784449568",
        "copyright": "弗拉维亚港, 苏尔西斯-伊格莱西恩特, 撒丁岛, 意大利 (© Marco Bottigelli/Getty Images)",
        "copyrightlink": "https://www.bing.com/search?q=%E5%BC%97%E6%8B%89%E7%BB%B4%E4%BA%9A%E6%B8%AF\u0026form=hpcapt\u0026mkt=zh-cn",
        "title": "矿石与传奇",
        "quiz": "/search?q=Bing+homepage+quiz\u0026filters=WQOskey:%22HPQuiz_20250513_SardiniaFlavia%22\u0026FORM=HPQUIZ",
        "wp": true,
        "hsh": "914ab88306492b21cb3c4f877abb7903",
        "drk": 1,
        "top": 1,
        "bot": 1,
        "hs": []
    }
}