{
    "20240816": {
        "startdate": "20240815",
        "fullstartdate": "202408151600",
        "enddate": "20240816",
        "url": "/th?id=OHR.JapanRollerCoaster_ZH-CN7954058301_1920x1080.jpg\u0026rf=LaDigue_1920x1080.jpg\u0026pid=hp",
        "urlbase": "/th?id=OHR.JapanRollerCoaster_ZH-CN7954058301",
        "copyright": "长岛温泉乐园的过山车，三重县，日本 (© Japanese amateur photographer/Getty Images)",
        "copyrightlink": "https://www.bing.com/search?q=%E9%95%BF%E5%B2%9B%E6%B8%A9%E6%B3%89%E4%B9%90%E5%9B%AD\u0026form=hpcapt\u0026mkt=zh-cn",
        "title": "系好安全带！",
        "quiz": "/search?q=Bing+homepage+quiz\u0026filters=WQOskey:%22HPQuiz_20240815_JapanRollerCoaster%22\u0026FORM=HPQUIZ",
        "wp": true,
        "hsh": "2c45e696d31703082c1d5dbcb61b8bc3",
        "drk": 1,
        "top": 1,
        "bot": 1,
        "hs": []
    }
}