{
    "20260226": {
        "startdate": "20260225",
        "fullstartdate": "202602251600",
        "enddate": "20260226",
        "url": "/th?id=OHR.GrandSunset_ZH-CN1905986519_1920x1080.jpg\u0026rf=LaDigue_1920x1080.jpg\u0026pid=hp",
        "urlbase": "/th?id=OHR.GrandSunset_ZH-CN1905986519",
        "copyright": "大峡谷和科罗拉多河，亚利桑那州，美国 (© Matt Anderson Photography/Getty Images)",
        "copyrightlink": "https://www.bing.com/search?q=%E7%BE%8E%E5%9B%BD%E5%A4%A7%E5%B3%A1%E8%B0%B7%E5%9B%BD%E5%AE%B6%E5%85%AC%E5%9B%AD\u0026form=hpcapt\u0026mkt=zh-cn",
        "title": "一幅壮丽的景象",
        "quiz": "/search?q=Bing+homepage+quiz\u0026filters=WQOskey:%22HPQuiz_20260225_GrandSunset%22\u0026FORM=HPQUIZ",
        "wp": true,
        "hsh": "8b5e695b3eb4caf2a66b15b3c1d0040a",
        "drk": 1,
        "top": 1,
        "bot": 1,
        "hs": []
    }
}